rfsed/ExtractEq.py
rfsed/ExtractEqMultiproc.py
rfsed/ReverbFilter.py
rfsed/SynthExp.py
rfsed/WaveformFitting.py
rfsed/WaveformFittingMultiproc.py
rfsed/__init__.py
rfsed/hkSeqYeck.py
rfsed/hkYu.py
rfsed/hkZhu.py
rfsed/util.py
rfsed/SynRF/FwdRF.py
rfsed/SynRF/__init__.py
rfsed/examples/scripts/00_example_Get_Catalog.py
rfsed/examples/scripts/01_example_ExtractEq.py
rfsed/examples/scripts/02_example_ExtractEqMultiproc.py
rfsed/examples/scripts/03_example_hkZhu.py
rfsed/examples/scripts/04_example_hkYeck_Sequential.py
rfsed/examples/scripts/05_example_reverbfilt_hkYu.py
rfsed/examples/scripts/06_example_SynthExp.py
rfsed/examples/scripts/07_example_WaveformFitting.py
rfsed/examples/scripts/08_example_WaveformFittingMultiproc.py
rfsed/examples/scripts/09_example_SynRF.py
rfsed/rf/__init__.py
rfsed/rf/batch.py
rfsed/rf/deconvolve.py
rfsed/rf/imaging.py
rfsed/rf/profile.py
rfsed/rf/rfstream.py
rfsed/rf/simple_model.py
rfsed/rf/util.py
rfsed/rf/example/create_example_files.py
rfsed/rf/tests/__init__.py
rfsed/rf/tests/__main__.py
rfsed/rf/tests/test_batch.py
rfsed/rf/tests/test_deconvolve.py
rfsed/rf/tests/test_imaging.py
rfsed/rf/tests/test_profile.py
rfsed/rf/tests/test_rfstream.py
rfsed/rf/tests/test_simple_model.py
rfsed/rf/tests/util.py
rfsed/tests/__init__.py
rfsed/tests/test_ExtractEq.py
rfsed/tests/test_ExtractEqMultiproc.py
rfsed/tests/test_ReverbFilter.py
rfsed/tests/test_WaveformFitting.py
rfsed/tests/test_WaveformFittingMultiproc.py
rfsed/tests/test_hkSeqYeck.py
rfsed/tests/test_hkYu.py
rfsed/tests/test_hkZhu.py
rfak-0.0.1.dist-info/LICENSE
rfak-0.0.1.dist-info/METADATA
rfak-0.0.1.dist-info/WHEEL
rfak-0.0.1.dist-info/top_level.txt
rfak-0.0.1.dist-info/RECORD
