Metadata-Version: 2.1
Name: rfak
Version: 0.0.1
Summary: A small example package
Home-page: https://github.com/akinremisa/rfsed
Author: Stephen Akinremi
Author-email: Example Author <author@example.com>
Keywords: Seismology,Receiver Function,Sediment effect in receiver functions,Crustal modelling,Moho,Earth Sciences
Classifier: Programming Language :: Python :: 3
Classifier: License :: OSI Approved :: MIT License
Classifier: Operating System :: OS Independent
Requires-Python: >=3.8
License-File: LICENSE
Requires-Dist: decorator
Requires-Dist: matplotlib
Requires-Dist: numpy
Requires-Dist: scipy
Requires-Dist: obspy >=1.0.3
Requires-Dist: tqdm
Requires-Dist: OWSLib
Requires-Dist: pytest
Requires-Dist: cartopy
Requires-Dist: geographiclib
Requires-Dist: shapely
Requires-Dist: seaborn
Requires-Dist: scikit-learn
Requires-Dist: h5
Requires-Dist: h5py
Requires-Dist: obspyh5
Requires-Dist: colorama ==0.1.6
Requires-Dist: plotly ==5.17.0
Requires-Dist: psutil ==5.9.6
Provides-Extra: docs
Requires-Dist: sphinx <6.0 ; extra == 'docs'
Requires-Dist: pydata-sphinx-theme ; extra == 'docs'
Requires-Dist: sphinx-copybutton ; extra == 'docs'
Requires-Dist: sphinx-gallery ; extra == 'docs'
Requires-Dist: jinja2 <3.1 ; extra == 'docs'
Provides-Extra: tests
Requires-Dist: pytest ; extra == 'tests'
Requires-Dist: py ; extra == 'tests'
